{
  "annotations": {
    "list": [
      {
        "builtIn": 1,
        "datasource": "-- Grafana --",
        "enable": true,
        "hide": true,
        "iconColor": "rgba(0, 211, 255, 1)",
        "name": "Annotations & Alerts",
        "type": "dashboard"
      }
    ]
  },
  "description": "This dashboard tracks metrics from the node validator via postgres DB",
  "editable": true,
  "gnetId": null,
  "graphTooltip": 0,
  "id": 1,
  "links": [],
  "panels": [
    {
      "aliasColors": {
        "Invalid": "red",
        "Pending verification": "super-light-blue"
      },
      "bars": true,
      "dashLength": 10,
      "dashes": false,
      "datasource": "PostgresSQL",
      "editable": true,
      "error": false,
      "fill": 0,
      "fillGradient": 0,
      "gridPos": {
        "h": 6,
        "w": 8,
        "x": 0,
        "y": 0
      },
      "id": 3,
      "interval": ">60m",
      "legend": {
        "avg": false,
        "current": false,
        "max": false,
        "min": false,
        "show": false,
        "total": false,
        "values": false
      },
      "lines": false,
      "linewidth": 1,
      "links": [],
      "nullPointMode": "connected",
      "options": {
        "dataLinks": []
      },
      "percentage": false,
      "pointradius": 1,
      "points": false,
      "renderer": "flot",
      "seriesOverrides": [
        {
          "alias": "test"
        }
      ],
      "spaceLength": 10,
      "stack": true,
      "steppedLine": false,
      "targets": [
        {
          "format": "time_series",
          "group": [
            {
              "params": [
                "$__interval",
                "none"
              ],
              "type": "time"
            }
          ],
          "metricColumn": "none",
          "rawQuery": false,
          "rawSql": "SELECT\n  $__time(time_column),\n  value1\nFROM\n  metric_table\nWHERE\n  $__timeFilter(time_column)\n",
          "refId": "B",
          "select": [
            [
              {
                "params": [
                  "\"validateState\""
                ],
                "type": "column"
              },
              {
                "params": [
                  "count"
                ],
                "type": "aggregate"
              },
              {
                "params": [
                  "Valid"
                ],
                "type": "alias"
              }
            ]
          ],
          "table": "\"default$default\".\"workUnit\"",
          "timeColumn": "\"validatedAt\"",
          "timeColumnType": "timestamp",
          "where": [
            {
              "name": "$__timeFilter",
              "params": [],
              "type": "macro"
            }
          ]
        }
      ],
      "thresholds": [],
      "timeFrom": null,
      "timeRegions": [],
      "timeShift": null,
      "title": "Valid Work Unit Counts",
      "tooltip": {
        "msResolution": false,
        "shared": true,
        "sort": 0,
        "value_type": "individual"
      },
      "type": "graph",
      "xaxis": {
        "buckets": null,
        "mode": "time",
        "name": null,
        "show": true,
        "values": []
      },
      "yaxes": [
        {
          "format": "short",
          "label": null,
          "logBase": 1,
          "max": null,
          "min": "0",
          "show": true
        },
        {
          "format": "short",
          "label": null,
          "logBase": 1,
          "max": null,
          "min": null,
          "show": true
        }
      ],
      "yaxis": {
        "align": false,
        "alignLevel": null
      }
    },
    {
      "aliasColors": {
        "Invalid": "red",
        "Pending verification": "super-light-blue"
      },
      "bars": true,
      "dashLength": 10,
      "dashes": false,
      "datasource": "PostgresSQL",
      "editable": true,
      "error": false,
      "fill": 0,
      "fillGradient": 0,
      "gridPos": {
        "h": 6,
        "w": 7,
        "x": 8,
        "y": 0
      },
      "id": 5,
      "interval": ">600s",
      "legend": {
        "alignAsTable": false,
        "avg": false,
        "current": false,
        "max": false,
        "min": false,
        "rightSide": false,
        "show": true,
        "total": true,
        "values": true
      },
      "lines": false,
      "linewidth": 1,
      "links": [],
      "nullPointMode": "connected",
      "options": {
        "dataLinks": []
      },
      "percentage": false,
      "pointradius": 1,
      "points": false,
      "renderer": "flot",
      "seriesOverrides": [
        {
          "alias": "Invalid",
          "yaxis": 1
        }
      ],
      "spaceLength": 10,
      "stack": false,
      "steppedLine": false,
      "targets": [
        {
          "format": "time_series",
          "group": [
            {
              "params": [
                "$__interval",
                "none"
              ],
              "type": "time"
            }
          ],
          "metricColumn": "none",
          "rawQuery": false,
          "rawSql": "SELECT\n  $__time(time_column),\n  value1\nFROM\n  metric_table\nWHERE\n  $__timeFilter(time_column)\n",
          "refId": "B",
          "select": [
            [
              {
                "params": [
                  "\"validateState\""
                ],
                "type": "column"
              },
              {
                "params": [
                  "count"
                ],
                "type": "aggregate"
              },
              {
                "params": [
                  "Pending"
                ],
                "type": "alias"
              }
            ]
          ],
          "table": "\"default$default\".\"workUnit\"",
          "timeColumn": "\"createdAt\"",
          "timeColumnType": "timestamp",
          "where": [
            {
              "name": "$__timeFilter",
              "params": [],
              "type": "macro"
            },
            {
              "datatype": "int4",
              "name": "",
              "params": [
                "\"validateState\"",
                "=",
                "0"
              ],
              "type": "expression"
            }
          ]
        },
        {
          "format": "time_series",
          "group": [
            {
              "params": [
                "$__interval",
                "none"
              ],
              "type": "time"
            }
          ],
          "metricColumn": "none",
          "rawQuery": false,
          "rawSql": "SELECT\n  $__time(time_column),\n  value1\nFROM\n  metric_table\nWHERE\n  $__timeFilter(time_column)\n",
          "refId": "A",
          "select": [
            [
              {
                "params": [
                  "\"validateState\""
                ],
                "type": "column"
              },
              {
                "params": [
                  "count"
                ],
                "type": "aggregate"
              },
              {
                "params": [
                  "Valid"
                ],
                "type": "alias"
              }
            ]
          ],
          "table": "\"default$default\".\"workUnit\"",
          "timeColumn": "\"createdAt\"",
          "timeColumnType": "timestamp",
          "where": [
            {
              "name": "$__timeFilter",
              "params": [],
              "type": "macro"
            },
            {
              "datatype": "int4",
              "name": "",
              "params": [
                "\"validateState\"",
                "=",
                "1"
              ],
              "type": "expression"
            }
          ]
        },
        {
          "format": "time_series",
          "group": [
            {
              "params": [
                "$__interval",
                "none"
              ],
              "type": "time"
            }
          ],
          "metricColumn": "none",
          "rawQuery": false,
          "rawSql": "SELECT\n  $__time(time_column),\n  value1\nFROM\n  metric_table\nWHERE\n  $__timeFilter(time_column)\n",
          "refId": "C",
          "select": [
            [
              {
                "params": [
                  "\"validateState\""
                ],
                "type": "column"
              },
              {
                "params": [
                  "count"
                ],
                "type": "aggregate"
              },
              {
                "params": [
                  "Invalid"
                ],
                "type": "alias"
              }
            ]
          ],
          "table": "\"default$default\".\"workUnit\"",
          "timeColumn": "\"createdAt\"",
          "timeColumnType": "timestamp",
          "where": [
            {
              "name": "$__timeFilter",
              "params": [],
              "type": "macro"
            },
            {
              "datatype": "int4",
              "name": "",
              "params": [
                "\"validateState\"",
                "=",
                "2"
              ],
              "type": "expression"
            }
          ]
        },
        {
          "format": "time_series",
          "group": [
            {
              "params": [
                "$__interval",
                "none"
              ],
              "type": "time"
            }
          ],
          "hide": true,
          "metricColumn": "none",
          "rawQuery": false,
          "rawSql": "SELECT\n  $__time(time_column),\n  value1\nFROM\n  metric_table\nWHERE\n  $__timeFilter(time_column)\n",
          "refId": "D",
          "select": [
            [
              {
                "params": [
                  "\"validateState\""
                ],
                "type": "column"
              },
              {
                "params": [
                  "count"
                ],
                "type": "aggregate"
              },
              {
                "params": [
                  "Pending verification"
                ],
                "type": "alias"
              }
            ]
          ],
          "table": "\"default$default\".\"workUnit\"",
          "timeColumn": "\"createdAt\"",
          "timeColumnType": "timestamp",
          "where": [
            {
              "name": "$__timeFilter",
              "params": [],
              "type": "macro"
            },
            {
              "datatype": "int4",
              "name": "",
              "params": [
                "\"validateState\"",
                "=",
                "4"
              ],
              "type": "expression"
            }
          ]
        },
        {
          "format": "time_series",
          "group": [
            {
              "params": [
                "$__interval",
                "none"
              ],
              "type": "time"
            }
          ],
          "metricColumn": "none",
          "rawQuery": false,
          "rawSql": "SELECT\n  $__time(time_column),\n  value1\nFROM\n  metric_table\nWHERE\n  $__timeFilter(time_column)\n",
          "refId": "E",
          "select": [
            [
              {
                "params": [
                  "\"validateState\""
                ],
                "type": "column"
              },
              {
                "params": [
                  "count"
                ],
                "type": "aggregate"
              },
              {
                "params": [
                  "Failed deadline"
                ],
                "type": "alias"
              }
            ]
          ],
          "table": "\"default$default\".\"workUnit\"",
          "timeColumn": "\"createdAt\"",
          "timeColumnType": "timestamp",
          "where": [
            {
              "name": "$__timeFilter",
              "params": [],
              "type": "macro"
            },
            {
              "datatype": "int4",
              "name": "",
              "params": [
                "\"validateState\"",
                "=",
                "5"
              ],
              "type": "expression"
            }
          ]
        }
      ],
      "thresholds": [],
      "timeFrom": null,
      "timeRegions": [],
      "timeShift": null,
      "title": "ValidateState WU Totals",
      "tooltip": {
        "msResolution": false,
        "shared": false,
        "sort": 0,
        "value_type": "individual"
      },
      "type": "graph",
      "xaxis": {
        "buckets": null,
        "mode": "series",
        "name": null,
        "show": true,
        "values": [
          "total"
        ]
      },
      "yaxes": [
        {
          "format": "short",
          "label": null,
          "logBase": 1,
          "max": null,
          "min": null,
          "show": true
        },
        {
          "format": "short",
          "label": null,
          "logBase": 1,
          "max": null,
          "min": null,
          "show": true
        }
      ],
      "yaxis": {
        "align": false,
        "alignLevel": null
      }
    },
    {
      "aliasColors": {},
      "bars": false,
      "dashLength": 10,
      "dashes": false,
      "datasource": "PostgresSQL",
      "editable": true,
      "error": false,
      "fill": 0,
      "fillGradient": 0,
      "gridPos": {
        "h": 6,
        "w": 9,
        "x": 15,
        "y": 0
      },
      "id": 7,
      "interval": ">600s",
      "legend": {
        "avg": false,
        "current": false,
        "max": false,
        "min": false,
        "show": true,
        "total": false,
        "values": false
      },
      "lines": true,
      "linewidth": 1,
      "links": [],
      "nullPointMode": "connected",
      "options": {
        "dataLinks": []
      },
      "percentage": false,
      "pointradius": 1,
      "points": false,
      "renderer": "flot",
      "seriesOverrides": [],
      "spaceLength": 10,
      "stack": false,
      "steppedLine": false,
      "targets": [
        {
          "format": "time_series",
          "group": [
            {
              "params": [
                "$__interval",
                "none"
              ],
              "type": "time"
            }
          ],
          "metricColumn": "none",
          "rawQuery": false,
          "rawSql": "SELECT\n  $__time(time_column),\n  value1\nFROM\n  metric_table\nWHERE\n  $__timeFilter(time_column)\n",
          "refId": "B",
          "select": [
            [
              {
                "params": [
                  "runtime"
                ],
                "type": "column"
              },
              {
                "params": [
                  "sum"
                ],
                "type": "aggregate"
              },
              {
                "params": [
                  "getDevices"
                ],
                "type": "alias"
              }
            ]
          ],
          "table": "\"default$default\".\"CronRun\"",
          "timeColumn": "\"createdAt\"",
          "timeColumnType": "timestamp",
          "where": [
            {
              "name": "$__timeFilter",
              "params": [],
              "type": "macro"
            },
            {
              "datatype": "text",
              "name": "",
              "params": [
                "\"jobName\"",
                "=",
                "'getDevices'"
              ],
              "type": "expression"
            }
          ]
        },
        {
          "format": "time_series",
          "group": [
            {
              "params": [
                "$__interval",
                "none"
              ],
              "type": "time"
            }
          ],
          "metricColumn": "none",
          "rawQuery": false,
          "rawSql": "SELECT\n  $__time(time_column),\n  value1\nFROM\n  metric_table\nWHERE\n  $__timeFilter(time_column)\n",
          "refId": "A",
          "select": [
            [
              {
                "params": [
                  "runtime"
                ],
                "type": "column"
              },
              {
                "params": [
                  "sum"
                ],
                "type": "aggregate"
              },
              {
                "params": [
                  "devicePowerRatings"
                ],
                "type": "alias"
              }
            ]
          ],
          "table": "\"default$default\".\"CronRun\"",
          "timeColumn": "\"createdAt\"",
          "timeColumnType": "timestamp",
          "where": [
            {
              "name": "$__timeFilter",
              "params": [],
              "type": "macro"
            },
            {
              "datatype": "text",
              "name": "",
              "params": [
                "\"jobName\"",
                "=",
                "'devicePowerRatings'"
              ],
              "type": "expression"
            }
          ]
        },
        {
          "format": "time_series",
          "group": [
            {
              "params": [
                "$__interval",
                "none"
              ],
              "type": "time"
            }
          ],
          "metricColumn": "none",
          "rawQuery": false,
          "rawSql": "SELECT\n  $__time(time_column),\n  value1\nFROM\n  metric_table\nWHERE\n  $__timeFilter(time_column)\n",
          "refId": "C",
          "select": [
            [
              {
                "params": [
                  "runtime"
                ],
                "type": "column"
              },
              {
                "params": [
                  "sum"
                ],
                "type": "aggregate"
              },
              {
                "params": [
                  "getRvnWork"
                ],
                "type": "alias"
              }
            ]
          ],
          "table": "\"default$default\".\"CronRun\"",
          "timeColumn": "\"createdAt\"",
          "timeColumnType": "timestamp",
          "where": [
            {
              "name": "$__timeFilter",
              "params": [],
              "type": "macro"
            },
            {
              "datatype": "text",
              "name": "",
              "params": [
                "\"jobName\"",
                "=",
                "'getRvnWork'"
              ],
              "type": "expression"
            }
          ]
        }
      ],
      "thresholds": [],
      "timeFrom": null,
      "timeRegions": [],
      "timeShift": null,
      "title": "CronJob Runtime Cost",
      "tooltip": {
        "msResolution": false,
        "shared": true,
        "sort": 0,
        "value_type": "individual"
      },
      "type": "graph",
      "xaxis": {
        "buckets": null,
        "mode": "time",
        "name": null,
        "show": true,
        "values": []
      },
      "yaxes": [
        {
          "format": "ms",
          "label": null,
          "logBase": 1,
          "max": null,
          "min": null,
          "show": true
        },
        {
          "format": "short",
          "label": null,
          "logBase": 1,
          "max": null,
          "min": null,
          "show": true
        }
      ],
      "yaxis": {
        "align": false,
        "alignLevel": null
      }
    },
    {
      "aliasColors": {},
      "bars": true,
      "dashLength": 10,
      "dashes": false,
      "datasource": "PostgresSQL",
      "editable": true,
      "error": false,
      "fill": 0,
      "fillGradient": 0,
      "gridPos": {
        "h": 6,
        "w": 8,
        "x": 0,
        "y": 6
      },
      "id": 1,
      "interval": ">600s",
      "legend": {
        "avg": false,
        "current": false,
        "max": false,
        "min": false,
        "show": true,
        "total": false,
        "values": false
      },
      "lines": false,
      "linewidth": 1,
      "links": [],
      "nullPointMode": "connected",
      "options": {
        "dataLinks": []
      },
      "percentage": false,
      "pointradius": 1,
      "points": false,
      "renderer": "flot",
      "seriesOverrides": [],
      "spaceLength": 10,
      "stack": true,
      "steppedLine": false,
      "targets": [
        {
          "format": "time_series",
          "group": [
            {
              "params": [
                "$__interval",
                "none"
              ],
              "type": "time"
            }
          ],
          "metricColumn": "none",
          "rawQuery": false,
          "rawSql": "SELECT\n  $__time(time_column),\n  value1\nFROM\n  metric_table\nWHERE\n  $__timeFilter(time_column)\n",
          "refId": "A",
          "select": [
            [
              {
                "params": [
                  "\"default$default\".\"DevicePowerRating\".\"rvnPower\""
                ],
                "type": "column"
              },
              {
                "params": [
                  "sum"
                ],
                "type": "aggregate"
              },
              {
                "params": [
                  "RVNPower"
                ],
                "type": "alias"
              }
            ]
          ],
          "table": "\"default$default\".\"DevicePowerRating\"",
          "timeColumn": "\"createdAt\"",
          "timeColumnType": "timestamp",
          "where": [
            {
              "name": "$__timeFilter",
              "params": [],
              "type": "macro"
            }
          ]
        },
        {
          "format": "time_series",
          "group": [
            {
              "params": [
                "$__interval",
                "none"
              ],
              "type": "time"
            }
          ],
          "metricColumn": "none",
          "rawQuery": false,
          "rawSql": "SELECT\n  $__time(time_column),\n  value1\nFROM\n  metric_table\nWHERE\n  $__timeFilter(time_column)\n",
          "refId": "B",
          "select": [
            [
              {
                "params": [
                  "\"default$default\".\"DevicePowerRating\".\"boincPower\""
                ],
                "type": "column"
              },
              {
                "params": [
                  "sum"
                ],
                "type": "aggregate"
              },
              {
                "params": [
                  "BoincPower"
                ],
                "type": "alias"
              }
            ]
          ],
          "table": "\"default$default\".\"DevicePowerRating\"",
          "timeColumn": "\"createdAt\"",
          "timeColumnType": "timestamp",
          "where": [
            {
              "name": "$__timeFilter",
              "params": [],
              "type": "macro"
            }
          ]
        }
      ],
      "thresholds": [],
      "timeFrom": null,
      "timeRegions": [],
      "timeShift": null,
      "title": "RVNPower vs BoincPower (per cronjob)",
      "tooltip": {
        "msResolution": false,
        "shared": true,
        "sort": 0,
        "value_type": "individual"
      },
      "type": "graph",
      "xaxis": {
        "buckets": null,
        "mode": "time",
        "name": null,
        "show": true,
        "values": []
      },
      "yaxes": [
        {
          "format": "short",
          "label": null,
          "logBase": 1,
          "max": null,
          "min": null,
          "show": true
        },
        {
          "format": "short",
          "label": null,
          "logBase": 1,
          "max": null,
          "min": null,
          "show": true
        }
      ],
      "yaxis": {
        "align": false,
        "alignLevel": null
      }
    },
    {
      "aliasColors": {},
      "bars": true,
      "dashLength": 10,
      "dashes": false,
      "datasource": "PostgresSQL",
      "editable": true,
      "error": false,
      "fill": 0,
      "fillGradient": 0,
      "gridPos": {
        "h": 6,
        "w": 7,
        "x": 8,
        "y": 6
      },
      "id": 6,
      "interval": ">600s",
      "legend": {
        "alignAsTable": false,
        "avg": false,
        "current": false,
        "max": false,
        "min": false,
        "rightSide": false,
        "show": true,
        "total": true,
        "values": true
      },
      "lines": false,
      "linewidth": 1,
      "links": [],
      "nullPointMode": "connected",
      "options": {
        "dataLinks": []
      },
      "percentage": false,
      "pointradius": 1,
      "points": false,
      "renderer": "flot",
      "seriesOverrides": [],
      "spaceLength": 10,
      "stack": false,
      "steppedLine": false,
      "targets": [
        {
          "format": "time_series",
          "group": [
            {
              "params": [
                "$__interval",
                "none"
              ],
              "type": "time"
            }
          ],
          "metricColumn": "none",
          "rawQuery": false,
          "rawSql": "SELECT\n  $__time(time_column),\n  value1\nFROM\n  metric_table\nWHERE\n  $__timeFilter(time_column)\n",
          "refId": "A",
          "select": [
            [
              {
                "params": [
                  "\"default$default\".\"DevicePowerRating\".\"rvnPower\""
                ],
                "type": "column"
              },
              {
                "params": [
                  "sum"
                ],
                "type": "aggregate"
              },
              {
                "params": [
                  "RVNPower"
                ],
                "type": "alias"
              }
            ]
          ],
          "table": "\"default$default\".\"DevicePowerRating\"",
          "timeColumn": "\"createdAt\"",
          "timeColumnType": "timestamp",
          "where": [
            {
              "name": "$__timeFilter",
              "params": [],
              "type": "macro"
            }
          ]
        },
        {
          "format": "time_series",
          "group": [
            {
              "params": [
                "$__interval",
                "none"
              ],
              "type": "time"
            }
          ],
          "metricColumn": "none",
          "rawQuery": false,
          "rawSql": "SELECT\n  $__time(time_column),\n  value1\nFROM\n  metric_table\nWHERE\n  $__timeFilter(time_column)\n",
          "refId": "B",
          "select": [
            [
              {
                "params": [
                  "\"default$default\".\"DevicePowerRating\".\"boincPower\""
                ],
                "type": "column"
              },
              {
                "params": [
                  "sum"
                ],
                "type": "aggregate"
              },
              {
                "params": [
                  "BoincPower"
                ],
                "type": "alias"
              }
            ]
          ],
          "table": "\"default$default\".\"DevicePowerRating\"",
          "timeColumn": "\"createdAt\"",
          "timeColumnType": "timestamp",
          "where": [
            {
              "name": "$__timeFilter",
              "params": [],
              "type": "macro"
            }
          ]
        }
      ],
      "thresholds": [],
      "timeFrom": null,
      "timeRegions": [],
      "timeShift": null,
      "title": "Boid Power Totals",
      "tooltip": {
        "msResolution": false,
        "shared": false,
        "sort": 0,
        "value_type": "individual"
      },
      "type": "graph",
      "xaxis": {
        "buckets": null,
        "mode": "series",
        "name": null,
        "show": true,
        "values": [
          "total"
        ]
      },
      "yaxes": [
        {
          "format": "short",
          "label": null,
          "logBase": 1,
          "max": null,
          "min": "0",
          "show": true
        },
        {
          "format": "short",
          "label": null,
          "logBase": 1,
          "max": null,
          "min": null,
          "show": true
        }
      ],
      "yaxis": {
        "align": false,
        "alignLevel": null
      }
    },
    {
      "aliasColors": {},
      "bars": false,
      "dashLength": 10,
      "dashes": false,
      "datasource": "PostgresSQL",
      "editable": true,
      "error": false,
      "fill": 0,
      "fillGradient": 0,
      "gridPos": {
        "h": 6,
        "w": 9,
        "x": 15,
        "y": 6
      },
      "id": 8,
      "interval": ">600s",
      "legend": {
        "avg": false,
        "current": false,
        "max": false,
        "min": false,
        "show": true,
        "total": false,
        "values": false
      },
      "lines": true,
      "linewidth": 1,
      "links": [],
      "nullPointMode": "connected",
      "options": {
        "dataLinks": []
      },
      "percentage": false,
      "pointradius": 1,
      "points": false,
      "renderer": "flot",
      "seriesOverrides": [],
      "spaceLength": 10,
      "stack": false,
      "steppedLine": false,
      "targets": [
        {
          "format": "time_series",
          "group": [
            {
              "params": [
                "$__interval",
                "none"
              ],
              "type": "time"
            }
          ],
          "metricColumn": "none",
          "rawQuery": true,
          "rawSql": "SELECT\n  floor(extract(epoch from \"createdAt\")/3600)*3600 AS \"time\",\n  sum(( regexp_split_to_array(split_part( results , ',',1 ),':'))[2]::int ) AS updatedWU\nFROM\n  \"default$default\".\"CronRun\"\nWHERE\n  $__timeFilter(\"createdAt\") AND\n  \"jobName\" = 'getBoincWork'\nGROUP BY 1\nORDER BY 1\n",
          "refId": "B",
          "select": [
            [
              {
                "params": [
                  "runtime"
                ],
                "type": "column"
              },
              {
                "params": [
                  "sum"
                ],
                "type": "aggregate"
              },
              {
                "params": [
                  "getDevices"
                ],
                "type": "alias"
              }
            ]
          ],
          "table": "\"default$default\".\"CronRun\"",
          "timeColumn": "\"createdAt\"",
          "timeColumnType": "timestamp",
          "where": [
            {
              "name": "$__timeFilter",
              "params": [],
              "type": "macro"
            },
            {
              "datatype": "text",
              "name": "",
              "params": [
                "\"jobName\"",
                "=",
                "'getDevices'"
              ],
              "type": "expression"
            }
          ]
        },
        {
          "format": "time_series",
          "group": [
            {
              "params": [
                "$__interval",
                "none"
              ],
              "type": "time"
            }
          ],
          "metricColumn": "none",
          "rawQuery": true,
          "rawSql": "SELECT\n  floor(extract(epoch from \"createdAt\")/3600)*3600 AS \"time\",\n  sum(( regexp_split_to_array(split_part( results , ',',2 ),':'))[2]::int ) AS newWU\nFROM\n  \"default$default\".\"CronRun\"\nWHERE\n  $__timeFilter(\"createdAt\") AND\n  \"jobName\" = 'getBoincWork'\nGROUP BY 1\nORDER BY 1\n",
          "refId": "A",
          "select": [
            [
              {
                "params": [
                  "runtime"
                ],
                "type": "column"
              },
              {
                "params": [
                  "sum"
                ],
                "type": "aggregate"
              },
              {
                "params": [
                  "getDevices"
                ],
                "type": "alias"
              }
            ]
          ],
          "table": "\"default$default\".\"CronRun\"",
          "timeColumn": "\"createdAt\"",
          "timeColumnType": "timestamp",
          "where": [
            {
              "name": "$__timeFilter",
              "params": [],
              "type": "macro"
            },
            {
              "datatype": "text",
              "name": "",
              "params": [
                "\"jobName\"",
                "=",
                "'getDevices'"
              ],
              "type": "expression"
            }
          ]
        },
        {
          "format": "time_series",
          "group": [
            {
              "params": [
                "$__interval",
                "none"
              ],
              "type": "time"
            }
          ],
          "metricColumn": "none",
          "rawQuery": true,
          "rawSql": "SELECT\n  floor(extract(epoch from \"createdAt\")/3600)*3600 AS \"time\",\n  sum(( regexp_split_to_array(split_part( results , ',',3 ),':'))[2]::int ) AS totalWU\nFROM\n  \"default$default\".\"CronRun\"\nWHERE\n  $__timeFilter(\"createdAt\") AND\n  \"jobName\" = 'getBoincWork'\nGROUP BY 1\nORDER BY 1\n",
          "refId": "C",
          "select": [
            [
              {
                "params": [
                  "runtime"
                ],
                "type": "column"
              },
              {
                "params": [
                  "sum"
                ],
                "type": "aggregate"
              },
              {
                "params": [
                  "getDevices"
                ],
                "type": "alias"
              }
            ]
          ],
          "table": "\"default$default\".\"CronRun\"",
          "timeColumn": "\"createdAt\"",
          "timeColumnType": "timestamp",
          "where": [
            {
              "name": "$__timeFilter",
              "params": [],
              "type": "macro"
            },
            {
              "datatype": "text",
              "name": "",
              "params": [
                "\"jobName\"",
                "=",
                "'getDevices'"
              ],
              "type": "expression"
            }
          ]
        }
      ],
      "thresholds": [],
      "timeFrom": null,
      "timeRegions": [],
      "timeShift": null,
      "title": "Work Units Ingest Statistics",
      "tooltip": {
        "msResolution": false,
        "shared": true,
        "sort": 0,
        "value_type": "individual"
      },
      "type": "graph",
      "xaxis": {
        "buckets": null,
        "mode": "time",
        "name": null,
        "show": true,
        "values": []
      },
      "yaxes": [
        {
          "format": "short",
          "label": null,
          "logBase": 1,
          "max": null,
          "min": null,
          "show": true
        },
        {
          "format": "short",
          "label": null,
          "logBase": 1,
          "max": null,
          "min": null,
          "show": true
        }
      ],
      "yaxis": {
        "align": false,
        "alignLevel": null
      }
    },
    {
      "aliasColors": {},
      "bars": true,
      "dashLength": 10,
      "dashes": false,
      "datasource": "PostgresSQL",
      "editable": true,
      "error": false,
      "fill": 0,
      "fillGradient": 0,
      "gridPos": {
        "h": 6,
        "w": 12,
        "x": 0,
        "y": 12
      },
      "id": 4,
      "interval": ">600s",
      "legend": {
        "alignAsTable": true,
        "avg": false,
        "current": true,
        "hideZero": true,
        "max": false,
        "min": false,
        "rightSide": true,
        "show": false,
        "sort": "current",
        "sortDesc": true,
        "total": false,
        "values": true
      },
      "lines": false,
      "linewidth": 1,
      "links": [],
      "nullPointMode": "connected",
      "options": {
        "dataLinks": []
      },
      "percentage": false,
      "pointradius": 1,
      "points": false,
      "renderer": "flot",
      "seriesOverrides": [],
      "spaceLength": 10,
      "stack": true,
      "steppedLine": false,
      "targets": [
        {
          "format": "time_series",
          "group": [
            {
              "params": [
                "$__interval",
                "none"
              ],
              "type": "time"
            }
          ],
          "metricColumn": "device",
          "rawQuery": false,
          "rawSql": "SELECT\n  $__time(time_column),\n  value1\nFROM\n  metric_table\nWHERE\n  $__timeFilter(time_column)\n",
          "refId": "A",
          "select": [
            [
              {
                "params": [
                  "\"default$default\".\"DevicePowerRating\".\"rvnPower\""
                ],
                "type": "column"
              },
              {
                "params": [
                  "max"
                ],
                "type": "aggregate"
              },
              {
                "params": [
                  "RVNPower"
                ],
                "type": "alias"
              }
            ]
          ],
          "table": "\"default$default\".\"DevicePowerRating\"",
          "timeColumn": "\"createdAt\"",
          "timeColumnType": "timestamp",
          "where": [
            {
              "name": "$__timeFilter",
              "params": [],
              "type": "macro"
            }
          ]
        },
        {
          "format": "time_series",
          "group": [
            {
              "params": [
                "$__interval",
                "none"
              ],
              "type": "time"
            }
          ],
          "hide": true,
          "metricColumn": "none",
          "rawQuery": false,
          "rawSql": "SELECT\n  $__time(time_column),\n  value1\nFROM\n  metric_table\nWHERE\n  $__timeFilter(time_column)\n",
          "refId": "B",
          "select": [
            [
              {
                "params": [
                  "\"default$default\".\"DevicePowerRating\".\"boincPower\""
                ],
                "type": "column"
              },
              {
                "params": [
                  "sum"
                ],
                "type": "aggregate"
              },
              {
                "params": [
                  "BoincPower"
                ],
                "type": "alias"
              }
            ]
          ],
          "table": "\"default$default\".\"DevicePowerRating\"",
          "timeColumn": "\"createdAt\"",
          "timeColumnType": "timestamp",
          "where": [
            {
              "name": "$__timeFilter",
              "params": [],
              "type": "macro"
            }
          ]
        }
      ],
      "thresholds": [],
      "timeFrom": null,
      "timeRegions": [],
      "timeShift": null,
      "title": "RVNPower Top 30",
      "tooltip": {
        "msResolution": false,
        "shared": true,
        "sort": 0,
        "value_type": "individual"
      },
      "type": "graph",
      "xaxis": {
        "buckets": null,
        "mode": "time",
        "name": null,
        "show": true,
        "values": []
      },
      "yaxes": [
        {
          "format": "short",
          "label": null,
          "logBase": 1,
          "max": null,
          "min": null,
          "show": true
        },
        {
          "format": "short",
          "label": null,
          "logBase": 1,
          "max": null,
          "min": null,
          "show": true
        }
      ],
      "yaxis": {
        "align": false,
        "alignLevel": null
      }
    },
    {
      "aliasColors": {},
      "bars": true,
      "dashLength": 10,
      "dashes": false,
      "datasource": "PostgresSQL",
      "editable": true,
      "error": false,
      "fill": 0,
      "fillGradient": 0,
      "gridPos": {
        "h": 6,
        "w": 12,
        "x": 12,
        "y": 12
      },
      "id": 2,
      "interval": ">600s",
      "legend": {
        "avg": false,
        "current": false,
        "max": false,
        "min": false,
        "show": false,
        "total": false,
        "values": false
      },
      "lines": false,
      "linewidth": 1,
      "links": [],
      "nullPointMode": "connected",
      "options": {
        "dataLinks": []
      },
      "percentage": false,
      "pointradius": 1,
      "points": false,
      "renderer": "flot",
      "seriesOverrides": [],
      "spaceLength": 10,
      "stack": true,
      "steppedLine": false,
      "targets": [
        {
          "format": "time_series",
          "group": [
            {
              "params": [
                "$__interval",
                "none"
              ],
              "type": "time"
            }
          ],
          "metricColumn": "none",
          "rawQuery": false,
          "rawSql": "SELECT\n  $__time(time_column),\n  value1\nFROM\n  metric_table\nWHERE\n  $__timeFilter(time_column)\n",
          "refId": "B",
          "select": [
            [
              {
                "params": [
                  "\"grantedCredit\""
                ],
                "type": "column"
              },
              {
                "params": [
                  "sum"
                ],
                "type": "aggregate"
              },
              {
                "params": [
                  "\"grantedCredit\""
                ],
                "type": "alias"
              }
            ]
          ],
          "table": "\"default$default\".\"workUnit\"",
          "timeColumn": "\"createdAt\"",
          "timeColumnType": "timestamp",
          "where": [
            {
              "name": "$__timeFilter",
              "params": [],
              "type": "macro"
            }
          ]
        }
      ],
      "thresholds": [],
      "timeFrom": null,
      "timeRegions": [],
      "timeShift": null,
      "title": "Granted Credits",
      "tooltip": {
        "msResolution": false,
        "shared": true,
        "sort": 0,
        "value_type": "individual"
      },
      "type": "graph",
      "xaxis": {
        "buckets": null,
        "mode": "time",
        "name": null,
        "show": true,
        "values": []
      },
      "yaxes": [
        {
          "format": "short",
          "label": null,
          "logBase": 1,
          "max": null,
          "min": null,
          "show": true
        },
        {
          "format": "short",
          "label": null,
          "logBase": 1,
          "max": null,
          "min": null,
          "show": true
        }
      ],
      "yaxis": {
        "align": false,
        "alignLevel": null
      }
    }
  ],
  "refresh": false,
  "schemaVersion": 19,
  "style": "dark",
  "tags": [],
  "templating": {
    "list": []
  },
  "time": {
    "from": "now-3h",
    "to": "now"
  },
  "timepicker": {
    "refresh_intervals": [
      "5s",
      "10s",
      "30s",
      "1m",
      "5m",
      "15m",
      "30m",
      "1h",
      "2h",
      "1d"
    ],
    "time_options": [
      "5m",
      "15m",
      "1h",
      "6h",
      "12h",
      "24h",
      "2d",
      "7d",
      "30d"
    ]
  },
  "timezone": "browser",
  "title": "Boid Node Validator v1.0",
  "uid": "000000010",
  "version": 5
}
